{
    "course": "MINE3212",
    "semester": "Semester 2, 2015",
    "isLinear": true,
    "manuallyModified": false,
    "calculable": true,
    "cutoff": [
        0,
        30,
        47,
        50,
        65,
        75,
        85
    ],
    "message": null,
    "assessment": [
        {
            "task": "Safety Inductions",
            "weight": "Pass/Fail"
        },
        {
            "task": "Week 1. Reaction Equilibria",
            "weight": "2"
        },
        {
            "task": "Week 2. Reaction Equilibria",
            "weight": "2"
        },
        {
            "task": "Week 3. Reaction /Phase Equilibria",
            "weight": "2"
        },
        {
            "task": "Heat and Mass Balance",
            "weight": "6"
        },
        {
            "task": "Week 7. Minor elements,gas/condensed phases",
            "weight": "2"
        },
        {
            "task": "Week 8. Kinetics, reaction mechanisms",
            "weight": "2"
        },
        {
            "task": "Week 10. Pb/Zn smelting",
            "weight": "2"
        },
        {
            "task": "Week 11. Ironmaking",
            "weight": "2"
        },
        {
            "task": "Week 12. Steelmaking",
            "weight": "2"
        },
        {
            "task": "Cu smelting process design report ",
            "weight": "18"
        },
        {
            "task": "Final examination",
            "weight": "60"
        }
    ],
    "related": []
}