{
    "course": "NURS7105",
    "semester": "Semester 2, 2015",
    "isLinear": true,
    "manuallyModified": false,
    "calculable": true,
    "cutoff": [
        0,
        30,
        47,
        50,
        65,
        75,
        85
    ],
    "message": null,
    "assessment": [
        {
            "task": "Synopsis",
            "weight": "10"
        },
        {
            "task": "Peer education session",
            "weight": "15"
        },
        {
            "task": "Padlet",
            "weight": "5"
        },
        {
            "task": "Essay",
            "weight": "20"
        },
        {
            "task": "Assessment Item 4",
            "weight": "50"
        }
    ],
    "related": []
}