{
    "course": "PSYC2311",
    "semester": "Semester 2, 2015",
    "isLinear": true,
    "manuallyModified": false,
    "calculable": true,
    "cutoff": [
        0,
        30,
        47,
        50,
        65,
        75,
        85
    ],
    "message": null,
    "assessment": [
        {
            "task": "Tutorial Participation",
            "weight": "20"
        },
        {
            "task": "Individual Case Report",
            "weight": "40"
        },
        {
            "task": "Online Quiz",
            "weight": "40"
        }
    ],
    "related": []
}