{
    "course": "RELN1510",
    "semester": "Semester 2, 2015",
    "isLinear": true,
    "manuallyModified": false,
    "calculable": true,
    "cutoff": [
        0,
        30,
        47,
        50,
        65,
        75,
        85
    ],
    "message": null,
    "assessment": [
        {
            "task": "Short Paper",
            "weight": "35"
        },
        {
            "task": "Long Paper",
            "weight": "55"
        },
        {
            "task": "Weekly Journal Entries",
            "weight": "10"
        }
    ],
    "related": []
}