{
    "course": "SPCH7827",
    "semester": "Semester 2, 2016",
    "isLinear": true,
    "manuallyModified": false,
    "calculable": true,
    "cutoff": [
        0,
        30,
        47,
        50,
        65,
        75,
        85
    ],
    "message": null,
    "assessment": [
        {
            "task": "Ethics decision making report ",
            "weight": "30"
        },
        {
            "task": "Planning, Providing, and Managing SP Services",
            "weight": "30"
        },
        {
            "task": "Case Integration Examination",
            "weight": "40"
        }
    ],
    "related": []
}