{
    "course": "ENVM3525",
    "semester": "Semester 2, 2015",
    "isLinear": true,
    "manuallyModified": false,
    "calculable": true,
    "cutoff": [
        0,
        30,
        47,
        50,
        65,
        75,
        85
    ],
    "message": null,
    "assessment": [
        {
            "task": "Sustainable Management Plan Presentation Component",
            "weight": "15"
        },
        {
            "task": "Sustainable Management Plan Report Component",
            "weight": "35"
        },
        {
            "task": "Case studies in sustainable business practice",
            "weight": "50"
        }
    ],
    "related": []
}