{
    "course": "ENVM2000",
    "semester": "Semester 2, 2015",
    "isLinear": true,
    "manuallyModified": false,
    "calculable": true,
    "cutoff": [
        0,
        30,
        47,
        50,
        65,
        75,
        85
    ],
    "message": null,
    "assessment": [
        {
            "task": "Workshop Quiz",
            "weight": "10"
        },
        {
            "task": "Assignment 1 - Questionnaire Analysis",
            "weight": "15"
        },
        {
            "task": "Assignment 2 - Paper Review",
            "weight": "10"
        },
        {
            "task": "Assignment 3 - Statistical Models",
            "weight": "15"
        },
        {
            "task": "Final Examination",
            "weight": "50"
        }
    ],
    "related": []
}