{
    "course": "SLAT7705",
    "semester": "Semester 2, 2015",
    "isLinear": true,
    "manuallyModified": false,
    "calculable": true,
    "cutoff": [
        0,
        30,
        47,
        50,
        65,
        75,
        85
    ],
    "message": null,
    "assessment": [
        {
            "task": "Chapter-based weekly worksheets",
            "weight": "40"
        },
        {
            "task": "Group worksheet presentation",
            "weight": "10"
        },
        {
            "task": "Part I Language code (Chapters 3-7)",
            "weight": "25"
        },
        {
            "task": "Part II Language use(Chapters 8-10 & 12)",
            "weight": "25"
        }
    ],
    "related": []
}