{
    "course": "BIOL1040",
    "semester": "Semester 1, 2016",
    "isLinear": true,
    "manuallyModified": false,
    "calculable": true,
    "cutoff": [
        0,
        30,
        47,
        50,
        65,
        75,
        85
    ],
    "message": null,
    "assessment": [
        {
            "task": "Practical Report - Toad Anatomy",
            "weight": "3"
        },
        {
            "task": "Practical Report - Osmosis",
            "weight": "3"
        },
        {
            "task": "Practical Report - Action Potential",
            "weight": "3"
        },
        {
            "task": "Practical Report - Skeletal Muscle",
            "weight": "3"
        },
        {
            "task": "Practical Report - Integration",
            "weight": "3"
        },
        {
            "task": "Practical Core Competencies (4)",
            "weight": "Pass/Fail"
        },
        {
            "task": "Personal Response",
            "weight": "6"
        },
        {
            "task": "PowerPoint Presentation",
            "weight": "5"
        },
        {
            "task": "Professional Response",
            "weight": "10"
        },
        {
            "task": "On-line Discussion",
            "weight": "5"
        },
        {
            "task": "Knowledge - Mastering Biology Quiz 1 - Modules 1&2",
            "weight": "3"
        },
        {
            "task": "Knowledge - Mastering Biology Quiz 2 - Modules 3&4",
            "weight": "3"
        },
        {
            "task": "Knowledge - Mastering Biology Quiz 3 - Modules 5&6",
            "weight": "3"
        },
        {
            "task": "Knowledge - Examination",
            "weight": "50"
        }
    ],
    "related": []
}