{
    "course": "EDUC3001",
    "semester": "Semester 1, 2016",
    "isLinear": true,
    "manuallyModified": false,
    "calculable": true,
    "cutoff": [
        0,
        30,
        47,
        50,
        65,
        75,
        85
    ],
    "message": null,
    "assessment": [
        {
            "task": "Weekly Activites",
            "weight": "20"
        },
        {
            "task": "Team-teaching using innovative learning sequence",
            "weight": "40"
        },
        {
            "task": "Critical Reflective Essay",
            "weight": "40"
        }
    ],
    "related": []
}