{
    "course": "EDUC6815",
    "semester": "Semester 1, 2016",
    "isLinear": true,
    "manuallyModified": false,
    "calculable": true,
    "cutoff": [
        0,
        30,
        47,
        50,
        65,
        75,
        85
    ],
    "message": null,
    "assessment": [
        {
            "task": "HPE Fundamentals",
            "weight": "15"
        },
        {
            "task": "Design an integrated HPE unit of work",
            "weight": "45"
        },
        {
            "task": "Teaching showcase interview",
            "weight": "40"
        }
    ],
    "related": []
}