{
    "course": "BIOT7002",
    "semester": "Semester 2, 2016",
    "isLinear": true,
    "manuallyModified": false,
    "calculable": true,
    "cutoff": [
        0,
        30,
        47,
        50,
        65,
        75,
        85
    ],
    "message": null,
    "assessment": [
        {
            "task": "Outline of research project",
            "weight": "5"
        },
        {
            "task": "Oral presentation of research findings",
            "weight": "15"
        },
        {
            "task": "Written report on research findings",
            "weight": "80"
        }
    ],
    "related": []
}