{
    "course": "ENVM3530",
    "semester": "Semester 2, 2016",
    "isLinear": true,
    "manuallyModified": false,
    "calculable": true,
    "cutoff": [
        0,
        30,
        47,
        50,
        65,
        75,
        85
    ],
    "message": null,
    "assessment": [
        {
            "task": "Progress note: Community group",
            "weight": "15"
        },
        {
            "task": "Catchment community participation report",
            "weight": "40"
        },
        {
            "task": "Environment and Community Written Examination",
            "weight": "45"
        }
    ],
    "related": []
}