{
    "course": "MECH4800",
    "semester": "Semester 2, 2016",
    "isLinear": true,
    "manuallyModified": false,
    "calculable": true,
    "cutoff": [
        0,
        30,
        47,
        50,
        65,
        75,
        85
    ],
    "message": null,
    "assessment": [
        {
            "task": "Tutorial 1 Reliability Analysis",
            "weight": "5"
        },
        {
            "task": "Tutorial 2 Heat Transfer",
            "weight": "5"
        },
        {
            "task": "Thermal Analysis Experiment",
            "weight": "15"
        },
        {
            "task": "Tutorial 3 Trajectory Optimisation Analysis",
            "weight": "10"
        },
        {
            "task": "Tutorial 4 Orbital Mechanics",
            "weight": "10"
        },
        {
            "task": "Final Exam",
            "weight": "55"
        }
    ],
    "related": []
}