{
    "course": "MIDW1008",
    "semester": "Semester 2, 2016",
    "isLinear": true,
    "manuallyModified": false,
    "calculable": true,
    "cutoff": [
        0,
        30,
        47,
        50,
        65,
        75,
        85
    ],
    "message": null,
    "assessment": [
        {
            "task": "Clinical Timesheet",
            "weight": "NGP"
        },
        {
            "task": "Continuity of Care Experiences / Births",
            "weight": "NGP"
        },
        {
            "task": "Medical Calculation Assessments 1 - 6",
            "weight": "NGP"
        },
        {
            "task": "Clinical Practice Assessment - Formative",
            "weight": "NGP"
        },
        {
            "task": "Mini OSCA - Medication Administration",
            "weight": "NGP"
        },
        {
            "task": "Clinical Practice Assessment - Summative",
            "weight": "NGP"
        }
    ],
    "related": []
}