{
    "course": "ENGG4103",
    "semester": "Semester 1, 2016",
    "isLinear": true,
    "manuallyModified": false,
    "calculable": true,
    "cutoff": [
        0,
        30,
        47,
        50,
        65,
        75,
        85
    ],
    "message": null,
    "assessment": [
        {
            "task": "Assignment No.1 Maintenance Strategy Formulation",
            "weight": "30"
        },
        {
            "task": "Practical No 1 Weibull/component replacement",
            "weight": "10"
        },
        {
            "task": "Assignment No.2 - Individual",
            "weight": "30"
        },
        {
            "task": "Practical No.2 Capital Replacement",
            "weight": "10"
        },
        {
            "task": "Assignment No.3 Mine Services Tutorials",
            "weight": "20"
        },
        {
            "task": "Quiz - Physical Asset Management",
            "weight": "20"
        }
    ],
    "related": []
}