{
    "course": "MICR3002",
    "semester": "Semester 1, 2016",
    "isLinear": true,
    "manuallyModified": false,
    "calculable": true,
    "cutoff": [
        0,
        30,
        47,
        50,
        65,
        75,
        85
    ],
    "message": null,
    "assessment": [
        {
            "task": "Practical write-up",
            "weight": "15"
        },
        {
            "task": "Research Project Paper",
            "weight": "25"
        },
        {
            "task": "End of semester exam",
            "weight": "60"
        }
    ],
    "related": []
}