{
    "course": "TOUR7040",
    "semester": "Semester 1, 2016",
    "isLinear": true,
    "manuallyModified": false,
    "calculable": true,
    "cutoff": [
        0,
        30,
        47,
        50,
        65,
        75,
        85
    ],
    "message": null,
    "assessment": [
        {
            "task": "Industry Project_Part A: Proposal presentation",
            "weight": "15"
        },
        {
            "task": "Industry Project_Part B: Group Project Portfolio ",
            "weight": "35"
        },
        {
            "task": "Individual Reflective Essay",
            "weight": "50"
        }
    ],
    "related": []
}